adnar_scraper/__init__.py
adnar_scraper/settings.py
adnar_scraper/scraper/__init__.py
adnar_scraper/scraper/scrapy_scraper/__init__.py
adnar_scraper/scraper/scrapy_scraper/examples/__init__.py
adnar_scraper/scraper/scrapy_scraper/examples/detail_info_scraper/__init__.py
adnar_scraper/scraper/scrapy_scraper/examples/detail_info_scraper/detail_info_scraper/__init__.py
adnar_scraper/scraper/scrapy_scraper/examples/detail_info_scraper/detail_info_scraper/items.py
adnar_scraper/scraper/scrapy_scraper/examples/detail_info_scraper/detail_info_scraper/middlewares.py
adnar_scraper/scraper/scrapy_scraper/examples/detail_info_scraper/detail_info_scraper/pipelines.py
adnar_scraper/scraper/scrapy_scraper/examples/detail_info_scraper/detail_info_scraper/settings.py
adnar_scraper/scraper/scrapy_scraper/examples/detail_info_scraper/detail_info_scraper/start_scraping.py
adnar_scraper/scraper/scrapy_scraper/examples/detail_info_scraper/detail_info_scraper/spiders/__init__.py
adnar_scraper/scraper/scrapy_scraper/examples/detail_info_scraper/detail_info_scraper/spiders/info_spider.py
adnar_scraper/scraper/scrapy_scraper/examples/detail_scraper_/__init__.py
adnar_scraper/scraper/scrapy_scraper/examples/detail_scraper_/detail_scraper/__init__.py
adnar_scraper/scraper/scrapy_scraper/examples/detail_scraper_/detail_scraper/items.py
adnar_scraper/scraper/scrapy_scraper/examples/detail_scraper_/detail_scraper/middlewares.py
adnar_scraper/scraper/scrapy_scraper/examples/detail_scraper_/detail_scraper/pipelines.py
adnar_scraper/scraper/scrapy_scraper/examples/detail_scraper_/detail_scraper/settings.py
adnar_scraper/scraper/scrapy_scraper/examples/detail_scraper_/detail_scraper/start_scraping.py
adnar_scraper/scraper/scrapy_scraper/examples/detail_scraper_/detail_scraper/spiders/__init__.py
adnar_scraper/scraper/scrapy_scraper/examples/detail_scraper_/detail_scraper/spiders/detail_spider.py
adnar_scraper/scraper/selenium_scraper/__init__.py
adnar_scraper-0.1.92.dist-info/LICENSE.txt
adnar_scraper-0.1.92.dist-info/METADATA
adnar_scraper-0.1.92.dist-info/WHEEL
adnar_scraper-0.1.92.dist-info/top_level.txt
adnar_scraper-0.1.92.dist-info/RECORD
